{
    "semester": "114-1",
    "list_info": {
        "部別": "進修部學士班",
        "科系": "企業管理學系",
        "班級": "進企管一(軍)",
        "選課代碼": "0668",
        "科目名稱": "體育",
        "科目英文名": "Physical Education",
        "學分": "2.0",
        "時數": "2.0",
        "必/選": "必修",
        "授課教師": "陳志豪",
        "教室": "軍方營區",
        "修課人數": "29",
        "上限人數": "60",
        "上課時間": "(四)3-4",
        "限修備註": "限修科系:企管學系(軍),",
        "備註": ""
    },
    "detail_raw_text": "回上一頁\t國立金門大學\t \n \t教學綱要\t \n\n部別 : 進修部學士班\t114學年度第1學期\t列印日期 : 2026/05/24\n科目名稱 : 體育 (Physical Education)\t開課班級 : 進企管一(軍)\t學　　分 : 2.0\t授課時數 : 2.0\n授課教師 : 陳志豪\t必選修 : 必修\t \t \n\n\n1.教學目標\n增進學生對體育運動的認識與興趣，培養學生良好的運動習慣和技能，進而 提升學生身體素質以及培養學生團隊合作、溝通協調等社會能力，進而促進學生的身心健康，增強體質。 \n\n\n2.教學綱要\n透過參與本體育課程讓學生可以瞭解參與體育活動的意義、功能及方法，並使其能運用於日常生活中。同時可以培養個人擅長的運動項目，確立運動嗜好，提升運動技能水準。也鼓勵同學可以做到定期適量運動，培養終身運動的良好生活習慣計畫。 \n\n\n3.教科書\n1\t書名 : 體育課程與教學專業　\n出版日期 : 2010年 09月 \n作者 : 周宏室　出版社 : 師大書苑出版社　版本 :  \n\n\n4.參考書\n1\t書名 : 體育教材教法　出版日期 : 2013年 09月 \n作者 : 葉憲清　出版社 : 師大書苑出版社　版本 :  \n\n※請遵守智慧財產權觀念，依著作權法規定，教科書及教材不得非法影印與使用盜版軟體。\n\n5.教學進度表\n週次\t日期\t內容\t備註\n1\t\n2025/09/14─2025/09/20\n\t基本動作機能練習I \t \n2\t\n2025/09/21─2025/09/27\n\t基本動作機能練習II \t \n3\t\n2025/09/28─2025/10/04\n\t基本動作機能練習III \t \n4\t\n2025/10/05─2025/10/11\n\t基本動作機能練習IV \t \n5\t\n2025/10/12─2025/10/18\n\t籃球I \t \n6\t\n2025/10/19─2025/10/25\n\t籃球II \t \n7\t\n2025/10/26─2025/11/01\n\t籃球III \t \n8\t\n2025/11/02─2025/11/08\n\t期中考 \t \n9\t\n2025/11/09─2025/11/15\n\t排球I \t \n10\t\n2025/11/16─2025/11/22\n\t排球II \t \n11\t\n2025/11/23─2025/11/29\n\t排球III \t \n12\t\n2025/11/30─2025/12/06\n\t羽球I \t \n13\t\n2025/12/07─2025/12/13\n\t羽球II \t \n14\t\n2025/12/14─2025/12/20\n\t羽球III \t \n15\t\n2025/12/21─2025/12/27\n\t期末考 \t \n16\t\n2025/12/28─2026/01/03\n\t元旦放假 \t \n17\t\n2026/01/04─2026/01/10\n\t彈性補充教學 \t \n18\t\n2026/01/11─2026/01/17\n\t彈性補充教學 \t \n\n\n6.成績評定及課堂要求\n體能測試，比賽成績。 \n出席並參與活動。 \n \n\n\n8.永續發展目標(SDGs)：SDG3 健康與福祉\n\n\n9.大學社會責任(USR)關聯性：中"
}