{
    "semester": "114-1",
    "list_info": {
        "部別": "日間部學士班",
        "科系": "土木與工程管理學系",
        "班級": "土木一",
        "選課代碼": "0178",
        "科目名稱": "微積分(一)",
        "科目英文名": "Calculus I",
        "學分": "3.0",
        "時數": "3.0",
        "必/選": "必修",
        "授課教師": "紀茂傑",
        "教室": "E102教室(理工大樓)",
        "修課人數": "43",
        "上限人數": "60",
        "上課時間": "(五)2-4",
        "限修備註": "",
        "備註": ""
    },
    "detail_raw_text": "回上一頁\t國立金門大學\t \n \t教學綱要\t \n\n部別 : 日間部學士班\t114學年度第1學期\t列印日期 : 2026/05/24\n科目名稱 : 微積分(一) (Calculus I)\t開課班級 : 土木一\t學　　分 : 3.0\t授課時數 : 3.0\n授課教師 : 紀茂傑\t必選修 : 必修\t \t \n\n\n1.教學目標\n1. 使學生對極限、導數、積分等基本概念的理解，以及對相關公式和定理的掌握及證明； 2. 掌握三維空間的向量、平面和直線的幾何性質和應用。掌握向量、平面和直線在三維空間的幾何性質和應用。 3. 培養學生分析問題、建立數學模型、並利用微積分進行計算和解決問題的能力，並為後續理工科系的學習打下堅實的數學基礎； 4. 提供學生了解以數學方法解決、分析工程與科學上的問題。  \n\n\n2.教學綱要\n1. 理解極限的概念，並能計算基本函數的極限。\n2. 掌握微分的定義、計算方法和應用，包括求導、極值分析等。\n3. 理解積分的定義、計算方法和應用，包括定積分、不定積分和面積計算等。\n4. 熟悉微積分基本定理，並能運用於解決相關問題。\n \n\n\n3.教科書\n1\t書名 : 微積分　\n出版日期 : 2023年 02月 \n作者 : 王牧民等　出版社 : 高立圖書　版本 : 二 \n\n\n4.參考書\n1\t書名 : Brief calculus and its applications　出版日期 : 2020年 06月 \n作者 : Goldstein, Lay, Schneider, Asmar　出版社 : Pearson　版本 : thirteenth edition \n\n※請遵守智慧財產權觀念，依著作權法規定，教科書及教材不得非法影印與使用盜版軟體。\n\n5.教學進度表\n週次\t日期\t內容\t備註\n1\t\n2025/09/14─2025/09/20\n\t課程簡介\n1簡介課程教學方式與評量標準\n2說明課程架構及進行方式\n3 微積分概要與微積分學習重要性介紹\n4說明本課程與學生核心能力之關連性\n \t \n2\t\n2025/09/21─2025/09/27\n\t函數\n1. 函數與圖形\n2. 三角函數\n \t \n3\t\n2025/09/28─2025/10/04\n\t函數\n3. 指數函數\n4. 對數函數\n5. 反函數　\n \t \n4\t\n2025/10/05─2025/10/11\n\t極限與連續性\n1. 極限的直觀\n2. 單側, 在無限遠之極限及無窮極限\n3. 極限的性質\n4. 極限之綜合例題\n \t \n5\t\n2025/10/12─2025/10/18\n\t極限與連續性\n1. 極限的直觀\n2. 單側, 在無限遠之極限及無窮極限\n3. 極限的性質\n4. 極限之綜合例題\n \t \n6\t\n2025/10/19─2025/10/25\n\t微分\n1. 由切線的概念導入微分\n2. 定義導函數及導數\n3. 導出微分的四則運算和合成運算的公式\n \t \n7\t\n2025/10/26─2025/11/01\n\t微分\n1. 隱函數微分\n2. 三角函數的導函數\n3. 反函數, 指數, 對數, 反三角函數之微分\n \t \n8\t\n2025/11/02─2025/11/08\n\t微分\n1. 雙曲函數的微分\n2. 微分應用, 包括變化率、 相對速率及線性估計\n \t \n9\t\n2025/11/09─2025/11/15\n\t期中評量 \t期中評量 \n10\t\n2025/11/16─2025/11/22\n\t微分應用\n1. 平均值定理\n2. 導函數在圖形上的意義3. 作圖\n \t \n11\t\n2025/11/23─2025/11/29\n\t微分應用\n1. 極值及其極值應用\n2. 其他應用: 不定型、牛頓法\n3. 反導函數\n \t \n12\t\n2025/11/30─2025/12/06\n\t積分\n1. 面積的估計\n2. 定積分\n3. 定積分性質\n \t \n13\t\n2025/12/07─2025/12/13\n\t積分\n1. 微積分基本定理\n2. 不定積分\n3. 變數變換\n \t \n14\t\n2025/12/14─2025/12/20\n\t積分應用\n1. 面積\n2. 切片法求體積\n3. 旋轉體體積\n \t \n15\t\n2025/12/21─2025/12/27\n\t積分應用\n1. 平面曲線之弧長\n2. 旋轉體側表面積\n3. 力矩與質心\n \t \n16\t\n2025/12/28─2026/01/03\n\t期末評量 \t期末評量 \n17\t\n2026/01/04─2026/01/10\n\t彈性教學 \t彈性教學 \n18\t\n2026/01/11─2026/01/17\n\t彈性教學 \t彈性教學 \n\n\n6.成績評定及課堂要求\n1. 課程參與 20% 2. 習題作業 20% 3. 期中評量30% 4. 期末評量30%  \n無 \n \n\n\n8.永續發展目標(SDGs)：SDG8 合適的工作及經濟成長、SDG9 工業化、創新及基礎建設\n\n\n9.大學社會責任(USR)關聯性：中"
}