{
    "semester": "114-2",
    "list_info": {
        "部別": "日間部學士班",
        "科系": "建築學系",
        "班級": "建築三",
        "選課代碼": "0239",
        "科目名稱": "建築計畫",
        "科目英文名": "Architectural Programming",
        "學分": "2.0",
        "時數": "2.0",
        "必/選": "必修",
        "授課教師": "吳松德",
        "教室": "111大陸事務專業教室",
        "修課人數": "31",
        "上限人數": "60",
        "上課時間": "(四)3-4",
        "限修備註": "",
        "備註": ""
    },
    "detail_raw_text": "回上一頁\t國立金門大學\t \n \t教學綱要\t \n\n部別 : 日間部學士班\t114學年度第2學期\t列印日期 : 2026/05/24\n科目名稱 : 建築計畫 (Architectural Programming)\t開課班級 : 建築三\t學　　分 : 2.0\t授課時數 : 2.0\n授課教師 : 吳松德\t必選修 : 必修\t \t \n\n\n1.教學目標\n建築計畫可視為建築設計的前段作業，在進行建築設計前，設計/規劃師從所有能取得的資訊中分析/離出需要界定的問題Problem Seeking，以科學研究與決策形成的過程，界定出要藉由設計來解決的問題 (例如：人性因素和機能、基地與環境物理條件、業主的想法與期望、成本與施工技術等等)。 \n\n\n2.教學綱要\n講述建築計畫學的內容與程序，並提供相關的學理基礎和適當的研究方法，透過建築計畫書的撰寫以滿足設計目標和需求，綜合基地分析、業主需求、使用者評估、空間計畫等內容，最後輔以國內外建築類型案例分析與計畫書內容架構，以尋求出最佳的設計方案之關聯性。 \n\n\n3.教科書\n1\t書名 : 圖解建築計畫理論與應用　\n出版日期 : 年 月 \n作者 : 池體演等　出版社 : 實力圖書　版本 :  \n2\t書名 : 建築計畫　\n出版日期 : 年 月 \n作者 : Robert Hershberger 呂以寧等譯　出版社 : 六合　版本 :  \n3\t書名 : 建築設計計畫　\n出版日期 : 年 月 \n作者 : Edith Cherry呂以寧譯　出版社 : 六合　版本 :  \n\n\n無參考書資料。\n\n※請遵守智慧財產權觀念，依著作權法規定，教科書及教材不得非法影印與使用盜版軟體。\n\n5.教學進度表\n週次\t日期\t內容\t備註\n1\t\n2026/02/22─2026/02/28\n\t課程簡介 \t \n2\t\n2026/03/01─2026/03/07\n\t建築計畫概論 \t \n3\t\n2026/03/08─2026/03/14\n\t建築計畫內容與程序 \t \n4\t\n2026/03/15─2026/03/21\n\t建築計畫表現與應用 \t \n5\t\n2026/03/22─2026/03/28\n\t建築計畫之構成---基地計畫 \t \n6\t\n2026/03/29─2026/04/04\n\t建築計畫之構成---建築空間計畫 \t \n7\t\n2026/04/05─2026/04/11\n\t建築計畫之構成---結構系統計畫 \t \n8\t\n2026/04/12─2026/04/18\n\t期中考試/報告 \t \n9\t\n2026/04/19─2026/04/25\n\t建築計畫之構成---物理環境與設備計畫 \t \n10\t\n2026/04/26─2026/05/02\n\t建築計畫之構成---建築構造計畫 \t \n11\t\n2026/05/03─2026/05/09\n\t建築計畫之構成---成本計劃及施工計畫 \t \n12\t\n2026/05/10─2026/05/16\n\t建築計畫之應用---住宅建築計畫 \t \n13\t\n2026/05/17─2026/05/23\n\t建築計畫之應用---辦公建築計畫 \t \n14\t\n2026/05/24─2026/05/30\n\t建築計畫之應用---圖書館建築計劃 \t \n15\t\n2026/05/31─2026/06/06\n\t建築計畫之應用---博物館建築計劃 \t \n16\t\n2026/06/07─2026/06/13\n\t建築計畫之應用---學校建築計畫 \t \n17\t\n2026/06/14─2026/06/20\n\t期末作業/報告 \t \n18\t\n2026/06/21─2026/06/27\n\t期末作業/報告 \t \n\n\n6.成績評定及課堂要求\n選項一：期中報告：35%、期末報告：30%、出席率或課程互動答題：35% 選項二：針對本課程架構或上課內容自訂報告題目（於第6週前提出題目）：65%、出席率或課程互動答題：35% 選項三：自主學習計畫，需於第3至第5週(2025.3.20)前提出自學計畫案並登記完成：100%（此選項以修課人數1/2為限） \n \n \n\n\n8.永續發展目標(SDGs)：SDG3 健康與福祉、SDG11 永續城鄉\n\n\n9.大學社會責任(USR)關聯性：中"
}