{
    "semester": "114-1",
    "list_info": {
        "部別": "進修部學士班",
        "科系": "觀光管理學系",
        "班級": "進觀光四",
        "選課代碼": "0591",
        "科目名稱": "宴會管理",
        "科目英文名": "Banquet project management",
        "學分": "2.0",
        "時數": "2.0",
        "必/選": "選修",
        "授課教師": "王芳堃",
        "教室": "231觀光系普通教室",
        "修課人數": "35",
        "上限人數": "60",
        "上課時間": "(五)1-2",
        "限修備註": "",
        "備註": ""
    },
    "detail_raw_text": "回上一頁\t國立金門大學\t \n \t教學綱要\t \n\n部別 : 進修部學士班\t114學年度第1學期\t列印日期 : 2026/05/24\n科目名稱 : 宴會管理 (Banquet project management)\t開課班級 : 進觀光四\t學　　分 : 2.0\t授課時數 : 2.0\n授課教師 : 王芳堃\t必選修 : 選修\t \t \n\n\n1.教學目標\n本課程涵蓋各式宴會之作業要點、流程及管理。 使學生能了解:會廳設備、宴會成本控制、宴會促銷活動、宴會作業流程，乃至中西宴會服務之安排、宴會菜單的設計、雞尾酒會和自助餐會之安排、外燴之安排、婚禮顧問之職掌與任務、宴會中葡萄酒之服務技巧，以及相關餐飲禮儀等 \n\n\n2.教學綱要\n本課程內容涵蓋:會廳設備、宴會成本控制、宴會促銷活動、宴會作業流程，乃至中西宴會服務之安排、宴會菜單的設計、雞尾酒會和自助餐會之安排、外燴之安排、婚禮顧問之職掌與任務、宴會中葡萄酒之服務技巧，以及相關餐飲禮儀等 \n\n\n3.教科書\n1\t書名 : 宴會管理：理論與實務　\n出版日期 : 年 月 \n作者 : 許順旺　出版社 : 揚智文化　版本 :  \n\n\n無參考書資料。\n\n※請遵守智慧財產權觀念，依著作權法規定，教科書及教材不得非法影印與使用盜版軟體。\n\n5.教學進度表\n週次\t日期\t內容\t備註\n1\t\n2025/09/14─2025/09/20\n\t會廳設備 \t \n2\t\n2025/09/21─2025/09/27\n\t宴會成本控制 \t \n3\t\n2025/09/28─2025/10/04\n\t宴會促銷活動 \t \n4\t\n2025/10/05─2025/10/11\n\t宴會作業流程 \t \n5\t\n2025/10/12─2025/10/18\n\t中西宴會服務之安排 \t \n6\t\n2025/10/19─2025/10/25\n\t宴會菜單設計 \t \n7\t\n2025/10/26─2025/11/01\n\t雞尾酒會和自助餐會之安排(一) \t \n8\t\n2025/11/02─2025/11/08\n\t雞尾酒會和自助餐會之安排(二) \t \n9\t\n2025/11/09─2025/11/15\n\t期中考 \t \n10\t\n2025/11/16─2025/11/22\n\t外燴安排 \t \n11\t\n2025/11/23─2025/11/29\n\t婚禮顧問之職掌與任務(一) \t \n12\t\n2025/11/30─2025/12/06\n\t婚禮顧問之職掌與任務(二) \t \n13\t\n2025/12/07─2025/12/13\n\t校外飯店宴會廳參訪 \t \n14\t\n2025/12/14─2025/12/20\n\t宴會中葡萄酒之服務技巧 \t \n15\t\n2025/12/21─2025/12/27\n\t餐飲禮儀 \t \n16\t\n2025/12/28─2026/01/03\n\t經營型態基本理論 \t \n17\t\n2026/01/04─2026/01/10\n\t標準作業流程 \t \n18\t\n2026/01/11─2026/01/17\n\t期末考 \t \n\n\n6.成績評定及課堂要求\n出席:30% 期中考:30% 期末考(或報告):40% \n \n \n\n\n8.永續發展目標(SDGs)：SDG4 優質教育、SDG11 永續城鄉\n\n\n9.大學社會責任(USR)關聯性：中"
}