{
    "semester": "112-2",
    "list_info": {
        "部別": "日間部學士班",
        "科系": "食品科學系",
        "班級": "食品一",
        "選課代碼": "0097",
        "科目名稱": "食物學原理",
        "科目英文名": "Food Fundamentals",
        "學分": "3.0",
        "時數": "3.0",
        "必/選": "選修",
        "授課教師": "黃積淵",
        "教室": "(五)E403教室(理工大樓),(五)E416食品工程實驗室",
        "修課人數": "33",
        "上限人數": "60",
        "上課時間": "(五)2-4",
        "限修備註": "",
        "備註": ""
    },
    "detail_raw_text": "回上一頁\t國立金門大學\t \n \t教學綱要\t \n\n部別 : 日間部學士班\t112學年度第2學期\t列印日期 : 2026/05/24\n科目名稱 : 食物學原理 (Food Fundamentals)\t開課班級 : 食品一\t學　　分 : 3.0\t授課時數 : 3.0\n授課教師 : 黃積淵\t必選修 : 選修\t \t \n\n\n1.教學目標\n使學生具備食物原料學,食品加工學,營養學,食品化學的基本知識,做為進一步更深入學習食品專業的基礎.學習成效(核心能力指標) 1.食品相關可利用生物資源調查及應用基礎。10% 2.食品專業基礎能力。30% 3.食品化學、食品加工及食品微生物等產業生產及研發能力。30% 4.食品分析檢驗及微生物技術檢驗能力。15% 5.食品專業整合能力。15% \n\n\n2.教學綱要\n教授穀類,蛋類,乳類,肉類,魚貝類,豆類,油脂類,蔬菜,水果,嗜好性飲料內容,使學生認識食品加工所用各種原料,提高學生學習興趣. \n\n\n3.教科書\n3\t書名 : 食物學原理　\n出版日期 : 年 月 \n作者 : 陳肅霖等十人　出版社 : 華格那出版有限公司　版本 :  \n\n\n4.參考書\n1\t書名 : 食物製備原理與應用　出版日期 : 年 月 \n作者 : 徐阿里等12人　出版社 : 華格那出版有限公司　版本 :  \n\n※請遵守智慧財產權觀念，依著作權法規定，教科書及教材不得非法影印與使用盜版軟體。\n\n5.教學進度表\n週次\t日期\t內容\t備註\n1\t\n2024/02/18─2024/02/24\n\t課程介紹 \t \n2\t\n2024/02/25─2024/03/02\n\t緒論 \t \n3\t\n2024/03/03─2024/03/09\n\t榖類介紹 \t \n4\t\n2024/03/10─2024/03/16\n\t蛋類介紹 \t \n5\t\n2024/03/17─2024/03/23\n\t乳類介紹 \t \n6\t\n2024/03/24─2024/03/30\n\t肉類介紹 \t \n7\t\n2024/03/31─2024/04/06\n\t肉類介紹 \t \n8\t\n2024/04/07─2024/04/13\n\t複習 \t \n9\t\n2024/04/14─2024/04/20\n\t期中考試 \t期中考試 \n10\t\n2024/04/21─2024/04/27\n\t魚貝類介紹 \t \n11\t\n2024/04/28─2024/05/04\n\t魚貝類介紹 \t \n12\t\n2024/05/05─2024/05/11\n\t豆類及其製品 \t \n13\t\n2024/05/12─2024/05/18\n\t油脂類介紹 \t \n14\t\n2024/05/19─2024/05/25\n\t蔬菜類 \t \n15\t\n2024/05/26─2024/06/01\n\t水果類 \t \n16\t\n2024/06/02─2024/06/08\n\t嗜好性飲料 \t \n17\t\n2024/06/09─2024/06/15\n\t複習 \t \n18\t\n2024/06/16─2024/06/22\n\t期末考試 \t期末考試 \n\n\n6.成績評定及課堂要求\n期中考30%,期末考30%,平時成績40% \n上課禁用手機,小考及繳交報告 \n \n\n\n8.永續發展目標(SDGs)：\n\n\n9.大學社會責任(USR)關聯性："
}