{
    "semester": "113-2",
    "list_info": {
        "部別": "日間部研究所碩士班",
        "科系": "國際暨大陸事務學系",
        "班級": "國際碩二",
        "選課代碼": "0257",
        "科目名稱": "金門政經發展與兩岸關係",
        "科目英文名": "Political & Economic Development in Kinmen and Across-Strait Relationship",
        "學分": "3.0",
        "時數": "3.0",
        "必/選": "選修",
        "授課教師": "林政緯",
        "教室": "108兩岸關係研究中心",
        "修課人數": "7",
        "上限人數": "30",
        "上課時間": "(六)5-7",
        "限修備註": "",
        "備註": ""
    },
    "detail_raw_text": "回上一頁\t國立金門大學\t \n \t教學綱要\t \n\n部別 : 日間部研究所碩士班\t113學年度第2學期\t列印日期 : 2026/05/24\n科目名稱 : 金門政經發展與兩岸關係 (Political & Economic Development in Kinmen and Across-Strait Relationship)\t開課班級 : 國際碩二\t學　　分 : 3.0\t授課時數 : 3.0\n授課教師 : 林政緯\t必選修 : 選修\t \t \n\n\n1.教學目標\n政治經濟學是以人們的社會生產關係和經濟關係作為研究對象的科學，探討政治與經濟的相互作用，闡明人類社會各個發展階段上支配物質資料的生產和分配的規律。本課程主要研究歷史演進歷程中，政治與經濟的相互作用及影響，透過每一階段不同的理論與經濟思維，探討各種經濟狀況的問題與發未來前景。金門具有悠久的發展歷史，亦在兩岸關係中具有重要且特殊的地位。1950年代，金門承擔戰地前線的使命，並於往後長達四十年的軍事化境遇中逐漸發展出不同於台灣的政治生態、經濟命脈與身分認同。在兩岸開啟交流之門以來，其戰略地位由政治軍事為主的高階政治層面，轉向以經濟社會為主的低階政治層面，並躍升為台灣與大陸之間的樞紐。本堂課程希望帶領同學了解金門、理解金門，並立足於金門來觀察兩岸關係的過去與現在，從而建構出對於兩岸前景分析的系統性思考。 \n\n\n2.教學綱要\n（一）課堂報告：前二週以教師授課為主。此後每次上課由一位同學進行指定閱讀報告，其他未報告的同學負責提問並針對該文章進行評論。教師會按照每周主題進行補充與相關時事分析。\n（二）課堂參與：鼓勵同學參與課堂討論，踴躍表達意見。\n（三）期末報告：於課程最後一週的下課時間前繳交期末報告至課程信箱，報告內容須與課程主題相關，並符合學術引用格式（請參考《政治學報》格式）。\n \n\n\n3.教科書\n4\t書名 : 宗親視野下的地方選舉：2018年金門縣五合一選舉個案分析　\n出版日期 : 2020年 12月 \n作者 : 林政緯主編　出版社 : 元華文創股份有限公司　版本 :  \n5\t書名 : 兩岸關係與政府大陸政策　\n出版日期 : 2019年 09月 \n作者 : 趙春山、郭瑞華等　出版社 : 三民書局股份有限公司　版本 : 修訂三版 \n6\t書名 : 重新檢視爭辯中的兩岸關係理論　\n出版日期 : 2012年 12月 \n作者 : 羅德明、張五岳等　出版社 : 五南　版本 : 二版 \n\n\n4.參考書\n1\t書名 : 《重商主義論》(Mercantilism)　出版日期 : 年 月 \n作者 : Thomas Mun 托馬斯‧孟著，周憲文譯　出版社 : 台北：台灣銀行經濟研究　版本 :  \n2\t書名 : 《魁奈「經濟表」及著作選》(Economic performance)　出版日期 : 年 月 \n作者 : Francois Quesnay 弗朗索瓦‧魁奈著，晏智杰譯　出版社 : 北京：華夏出版社　版本 :  \n3\t書名 : 《國富論》 (The Wealth of Nations)　出版日期 : 年 月 \n作者 : .Adam Smith 亞當‧史密斯著，謝宗林、李華夏譯　出版社 : 台北：先覺出版社　版本 :  \n4\t書名 : 《政治經濟學及賦稅原理》(On the Principles of Political Economy and Taxation)　出版日期 : 年 月 \n作者 : Ricardo, D.大衛‧李嘉圖著，郭大力、王亞南譯　出版社 : 南京：譯林出版社　版本 :  \n5\t書名 : 《資本論》(Das Kapital)　出版日期 : 年 月 \n作者 : Karl Marx 卡爾‧馬克思著，中共中央馬克思恩格斯列寧斯大林著作編　出版社 : 台北：聯經出版社　版本 :  \n6\t書名 : 《經濟學原理》(Principles of Economics)　出版日期 : 年 月 \n作者 : Alfred Marshall 阿爾佛雷德‧馬歇爾著，宇琦譯　出版社 : 湖南：湖南大學文藝出版社　版本 :  \n7\t書名 : 《福利經濟學》(Welfare economics)　出版日期 : 年 月 \n作者 : Arthur Cecil Pigou 亞瑟‧塞西爾‧庇古著，金鏑譯，晏智杰主編　出版社 : 北京：華夏出版社　版本 :  \n8\t書名 : 《經濟發展理論》(Theory of Economic Development)　出版日期 : 年 月 \n作者 : Jeseph A. Schumpeter 約瑟夫‧熊彼得著，何畏、易家詳譯，李華夏審定　出版社 : 台北：左岸文化出版　版本 :  \n9\t書名 : 《就業、利息和貨幣通論》(The General Theory of Employment, Interest, and Money)　出版日期 : 年 月 \n作者 : John Maynard Keynes 約翰‧梅納德‧凱恩斯著，高鴻業譯　出版社 : 北京：商務印書館　版本 :  \n10\t書名 : 《到奴役之路》(The Road to Serfdom)　出版日期 : 年 月 \n作者 : Friedrich August von Hayek 弗里德里希‧奧古斯都‧馮‧海耶克著，殷海光　出版社 : 台北：台大出版中心　版本 :  \n11\t書名 : 《致命的自負》(The Fatal Conceit)　出版日期 : 年 月 \n作者 : Friedrich August von Hayek 弗里德里希‧奧古斯都‧馮‧海耶克著，殷海光　出版社 : 北京：中國社會科學出版社　版本 :  \n12\t書名 : 《資本主義與自由》(Capitalism and Freedom)　出版日期 : 年 月 \n作者 : Milton Friedman 密爾頓‧傅利曼著，謝宗林譯　出版社 : 台北：博雅書屋　版本 :  \n13\t書名 : 《選擇的自由》(Free to Choose)　出版日期 : 年 月 \n作者 : Milton Friedman 米爾頓‧傅利曼、Rose Friedman 羅絲‧傅利曼著，羅耀宗譯　出版社 : 台北：經濟新潮社　版本 :  \n14\t書名 : 《廠商、市場與法律》(The Firm, the Market and the Law)　出版日期 : 年 月 \n作者 : Ronald Harry Coase 羅納德‧寇斯著，陳坤銘，李華夏譯　出版社 : 台北：遠流出版社　版本 :  \n15\t書名 : 《制度、制度變遷與經濟成就》(Institutions，Institutional Change and Economic Performance)　出版日期 : 年 月 \n作者 : Douglass C. North 道格拉斯‧諾斯著，劉瑞華譯　出版社 : 台北：聯經出版社　版本 :  \n16\t書名 : 《經濟史的結構與變遷》(Structure and Change in Economic History)　出版日期 : 年 月 \n作者 : Douglass C. North 道格拉斯‧諾斯著，劉瑞華譯　出版社 : 台北：聯經出版社　版本 :  \n17\t書名 : 《財富大逃亡-健康、財富與 不平等的起源》(The Great Escape: Health, Wealth, and the Origins of Inequality)　出版日期 : 年 月 \n作者 : Angus Deaton 安格斯‧迪頓著，李隆生、張逸安譯　出版社 : 台北：聯經出版社　版本 :  \n18\t書名 : 《資本主義、社會主義與民主》(Capitalism, Socialism and Democracy)　出版日期 : 年 月 \n作者 : Jeseph A. Schumpeter 約瑟夫‧熊彼得著，吳良健譯　出版社 : 台北：左岸文化出版　版本 :  \n\n※請遵守智慧財產權觀念，依著作權法規定，教科書及教材不得非法影印與使用盜版軟體。\n\n5.教學進度表\n週次\t日期\t內容\t備註\n1\t\n2025/02/16─2025/02/22\n\t課程說明與評分方式介紹 \t \n2\t\n2025/02/23─2025/03/01\n\t金門的歷史與現況概述 \t \n3\t\n2025/03/02─2025/03/08\n\t金門的發展：政治、經濟與社會治理Ⅰ \t \n4\t\n2025/03/09─2025/03/15\n\t金門的發展：政治、經濟與社會治理Ⅱ \t \n5\t\n2025/03/16─2025/03/22\n\t金門的發展：政治、經濟與社會治理Ⅲ \t \n6\t\n2025/03/23─2025/03/29\n\t兩岸關係的研究途徑：理論探討與策略選擇 \t \n7\t\n2025/03/30─2025/04/05\n\t兩岸互動的影響因子（一）：認同與經濟因素Ⅰ \t \n8\t\n2025/04/06─2025/04/12\n\t兩岸互動的影響因子（一）：認同與經濟因素Ⅱ \t \n9\t\n2025/04/13─2025/04/19\n\t兩岸關係的影響因子（二）：交流或統戰Ⅰ \t \n10\t\n2025/04/20─2025/04/26\n\t兩岸關係的影響因子（二）：交流或統戰Ⅱ \t \n11\t\n2025/04/27─2025/05/03\n\t兩岸關係的影響因子（三）：國際因素Ⅰ \t \n12\t\n2025/05/04─2025/05/10\n\t兩岸關係的影響因子（三）：國際因素Ⅱ \t \n13\t\n2025/05/11─2025/05/17\n\t中共對台政策（一）：組織與手段Ⅰ \t \n14\t\n2025/05/18─2025/05/24\n\t中共對台政策（一）：組織與手段Ⅱ \t \n15\t\n2025/05/25─2025/05/31\n\t中共對台政策（二）：認知作戰與信任問題 \t \n16\t\n2025/06/01─2025/06/07\n\t期末報告 \t \n17\t\n2025/06/08─2025/06/14\n\t彈性學習 \t \n18\t\n2025/06/15─2025/06/21\n\t自主學習 \t \n\n\n6.成績評定及課堂要求\n（一）課堂報告（30％） （二）課堂參與（30％） （三）期末報告（40％） 額外加分：時事預測、學術活動參與、電影或演講心得及課堂筆記等。 \n \n課程內容及進度依實際上課狀況彈性調整。 \n\n\n8.永續發展目標(SDGs)：SDG4 優質教育、SDG10 減少不平等\n\n\n9.大學社會責任(USR)關聯性：中"
}