{
    "semester": "112-2",
    "list_info": {
        "部別": "日間部學士班",
        "科系": "護理學系",
        "班級": "護理三",
        "選課代碼": "0737",
        "科目名稱": "兒科護理學",
        "科目英文名": "Pediatric Nursing",
        "學分": "3.0",
        "時數": "3.0",
        "必/選": "必修",
        "授課教師": "黃玉苹",
        "教室": "D203護理系普通教室",
        "修課人數": "38",
        "上限人數": "45",
        "上課時間": "(四)2-4",
        "限修備註": "限修科系:護理學系,先修科目:內外科護理學I 0分,內外科護理學II 0分,",
        "備註": ""
    },
    "detail_raw_text": "回上一頁\t國立金門大學\t \n \t教學綱要\t \n\n部別 : 日間部學士班\t112學年度第2學期\t列印日期 : 2026/05/24\n科目名稱 : 兒科護理學 (Pediatric Nursing)\t開課班級 : 護理三\t學　　分 : 3.0\t授課時數 : 3.0\n授課教師 : 黃玉苹\t必選修 : 必修\t \t \n\n\n1.教學目標\n1. 能解釋兒科常見疾病的病理生理、臨床症狀、診斷檢查、醫療處置及護理照護。 2. 能認識住院及疾病對不同發展階段病童及家庭影響。 3. 能認識以家庭為中心照護理念提供病童及家庭個別性照護。 4. 能認識兒童及父母溝通技巧及治療性遊戲。 5. 能認識兒科護理人員的角色與功能。  \n\n\n2.教學綱要\n本課程目的為基兒科護理人員的角色及功能、以家庭為中心及發展概念，融合基礎醫療知識，提供學生了解疾病及住院對病童及家庭身、心、靈、社會及文化的影響，進而瞭解個別性照護的重要性，以發展整體照護病童及其家庭的知識及能力。 \n\n\n3.教科書\n1\t書名 : 實用兒科護理學　\n出版日期 : 2018年 09月 \n作者 : 陳月枝等著（2017）　出版社 : 台北：華杏　版本 : 八版 \n\n\n4.參考書\n1\t書名 : Wong's Nursing Care of Infants and Children　出版日期 : 年 月 \n作者 : Marilyn J. Hockenberry, M. J. & Wilson, D.　出版社 : St. Louis：Mosby　版本 :  \n2\t書名 : 兒科身體檢查圖解手冊　出版日期 : 年 月 \n作者 : 林明志、黃彌淑譯　出版社 : 台北：台灣愛思唯爾　版本 :  \n3\t書名 : 　出版日期 : 年 月 \n作者 : 　出版社 : 　版本 :  \n\n※請遵守智慧財產權觀念，依著作權法規定，教科書及教材不得非法影印與使用盜版軟體。\n\n5.教學進度表\n週次\t日期\t內容\t備註\n1\t\n2024/02/18─2024/02/24\n\t課程簡介+緒論住院兒童的反應及護理 \t \n2\t\n2024/02/25─2024/03/02\n\t溝通技巧及治療性遊戲 \t \n3\t\n2024/03/03─2024/03/09\n\t兒童呼吸系統疾病及護理 \t \n4\t\n2024/03/10─2024/03/16\n\t兒童循環系統疾病及護理 \t \n5\t\n2024/03/17─2024/03/23\n\t兒童消化系統疾病及護理、腸病毒 \t \n6\t\n2024/03/24─2024/03/30\n\t兒童泌尿系統護理 \t \n7\t\n2024/03/31─2024/04/06\n\t兒童血液系統疾病及護理 \t \n8\t\n2024/04/07─2024/04/13\n\t國定假日 \t \n9\t\n2024/04/14─2024/04/20\n\t期中考 \t \n10\t\n2024/04/21─2024/04/27\n\t內分泌系統護理 \t \n11\t\n2024/04/28─2024/05/04\n\t傳染性疾病及其照護 \t \n12\t\n2024/05/05─2024/05/11\n\t兒童神經系統疾病及護理兒童\n肌肉骨骼系統疾病及護理 \t \n13\t\n2024/05/12─2024/05/18\n\t癌症病童之護理 \t \n14\t\n2024/05/19─2024/05/25\n\t瀕死病童的護理\n慢性病兒童及其家庭護理 \t \n15\t\n2024/05/26─2024/06/01\n\t兒童青少年發展及心理兒童事故傷害的防範與護理健康問題及照護 \t \n16\t\n2024/06/02─2024/06/08\n\t新生兒先天性疾病篩檢與照護 \t \n17\t\n2024/06/09─2024/06/15\n\t高危險性新生兒護理 \t \n18\t\n2024/06/16─2024/06/22\n\t期末考 \t \n\n\n6.成績評定及課堂要求\n第一次小考(15%)、第二次小考(15%)、期中考(20%)、 期末考(20%)、VR測驗使用(10%)、英文病例翻譯(10%) \n上課參與程度佔(10%)。以100分計算，缺課一週扣15分，遲到扣5分，以累加計算，累積達5週缺課或遲到，此項以0分計算。 \n \n\n\n8.永續發展目標(SDGs)：\n\n\n9.大學社會責任(USR)關聯性："
}