{
    "semester": "113-2",
    "list_info": {
        "部別": "日間部研究所碩士班",
        "科系": "觀光管理學系",
        "班級": "觀光碩一",
        "選課代碼": "0544",
        "科目名稱": "島嶼資源專題",
        "科目英文名": "The Topic of Island Resources",
        "學分": "2.0",
        "時數": "2.0",
        "必/選": "選修",
        "授課教師": "黃茱珺",
        "教室": "228旅遊導覽解說教室",
        "修課人數": "12",
        "上限人數": "30",
        "上課時間": "(一)10-11",
        "限修備註": "",
        "備註": ""
    },
    "detail_raw_text": "回上一頁\t國立金門大學\t \n \t教學綱要\t \n\n部別 : 日間部研究所碩士班\t113學年度第2學期\t列印日期 : 2026/05/24\n科目名稱 : 島嶼資源專題 (The Topic of Island Resources)\t開課班級 : 觀光碩一\t學　　分 : 2.0\t授課時數 : 2.0\n授課教師 : 黃茱珺\t必選修 : 選修\t \t \n\n\n1.教學目標\n藉由島嶼獨特的空間特性與發展，探討島嶼如何與環境互動，如何被看待與思考，以及島嶼觀光的展現。 \n\n\n2.教學綱要\n1.瞭解島嶼特性\n2.研究島嶼觀光資源 \n\n\n3.教科書\n1\t書名 : 自編講義　\n出版日期 : 年 月 \n作者 : 黃茱珺老師　出版社 : 　版本 :  \n\n\n4.參考書\n1\t書名 : 學術期刊　出版日期 : 年 月 \n作者 : 　出版社 : 　版本 :  \n\n※請遵守智慧財產權觀念，依著作權法規定，教科書及教材不得非法影印與使用盜版軟體。\n\n5.教學進度表\n週次\t日期\t內容\t備註\n1\t\n2025/02/16─2025/02/22\n\t期刊導讀分配 \t \n2\t\n2025/02/23─2025/03/01\n\t摘要~結構分析\n \t \n3\t\n2025/03/02─2025/03/08\n\t前言~結構分析\n\n \t \n4\t\n2025/03/09─2025/03/15\n\t前言~練習前言結構內容 \t \n5\t\n2025/03/16─2025/03/22\n\t前言~練習前言結構內容 \t \n6\t\n2025/03/23─2025/03/29\n\t前言~練習前言結構內容 \t \n7\t\n2025/03/30─2025/04/05\n\t文獻回顧~結構分析 \t \n8\t\n2025/04/06─2025/04/12\n\t文獻回顧~結構分析 \t \n9\t\n2025/04/13─2025/04/19\n\t文獻回顧~結構分析 \t \n10\t\n2025/04/20─2025/04/26\n\t練習寫文獻回顧結構 \t \n11\t\n2025/04/27─2025/05/03\n\t練習寫文獻回顧結構 \t \n12\t\n2025/05/04─2025/05/10\n\t研究方法探討 \t \n13\t\n2025/05/11─2025/05/17\n\t研究方法探討 \t \n14\t\n2025/05/18─2025/05/24\n\t練習寫研究方法 \t \n15\t\n2025/05/25─2025/05/31\n\t練習寫研究方法 \t \n16\t\n2025/06/01─2025/06/07\n\t期末交流 \t \n17\t\n2025/06/08─2025/06/14\n\t自主學習 \t \n18\t\n2025/06/15─2025/06/21\n\t自主學習 \t \n\n\n6.成績評定及課堂要求\n出席率 25% 期中報告30 期末報告45% \n \n \n\n\n8.永續發展目標(SDGs)：SDG11 永續城鄉、SDG12 責任消費及生產\n\n\n9.大學社會責任(USR)關聯性：中"
}