{
    "semester": "112-1",
    "list_info": {
        "部別": "進修部學士班",
        "科系": "觀光管理學系",
        "班級": "進觀光一",
        "選課代碼": "0618",
        "科目名稱": "兩岸旅遊政經分析",
        "科目英文名": "Analysis on Cross-Strait Development in Tourism by Political Economy Approach",
        "學分": "2.0",
        "時數": "2.0",
        "必/選": "選修",
        "授課教師": "陳向鑫",
        "教室": "232觀光系普通教室",
        "修課人數": "42",
        "上限人數": "60",
        "上課時間": "(五)3-4",
        "限修備註": "",
        "備註": ""
    },
    "detail_raw_text": "回上一頁\t國立金門大學\t \n \t教學綱要\t \n\n部別 : 進修部學士班\t112學年度第1學期\t列印日期 : 2026/05/24\n科目名稱 : 兩岸旅遊政經分析 (Analysis on Cross-Strait Development in Tourism by Political Economy Approach)\t開課班級 : 進觀光一\t學　　分 : 2.0\t授課時數 : 2.0\n授課教師 : 陳向鑫\t必選修 : 選修\t \t \n\n\n1.教學目標\n讓學生對兩岸情勢有進一步認知，並從中觀察旅遊經濟活動的變化。 \n\n\n2.教學綱要\n一、兩岸關係與旅遊交流進程。\n二、兩岸經濟發展與全球經濟情勢分析。 \n\n\n3.教科書\n1\t書名 : 大陸出境旅遊與兩岸關係之政治分析　\n出版日期 : 年 月 \n作者 : 范世平　出版社 : 秀威　版本 :  \n\n\n4.參考書\n1\t書名 : 博奕娛樂事業概論　出版日期 : 年 月 \n作者 : 郭春敏　出版社 : 揚智文化　版本 :  \n2\t書名 : 大陸旅遊研究　出版日期 : 年 月 \n作者 : 范世平　出版社 : 　版本 :  \n3\t書名 : 兩岸政經發展學術研討會論文集　出版日期 : 年 月 \n作者 : 國立金門大學　出版社 : 　版本 :  \n4\t書名 : 　出版日期 : 年 月 \n作者 : 　出版社 : 　版本 :  \n\n※請遵守智慧財產權觀念，依著作權法規定，教科書及教材不得非法影印與使用盜版軟體。\n\n5.教學進度表\n週次\t日期\t內容\t備註\n1\t\n2023/9/10 -2023/9/16\n\t預備週\n課程介紹 \t \n2\t\n2023/9/17 -2023/9/23\n\t兩岸關係概述 \t \n3\t\n2023/9/24 -2023/9/30\n\t兩岸關係概述 \t \n4\t\n2023/10/1 -2023/10/7\n\t小三通 \t \n5\t\n2023/10/8 -2023/10/14\n\t辜汪會談 \t \n6\t\n2023/10/15-2023/10/21\n\t江陳會談 \t \n7\t\n2023/10/22-2023/10/28\n\t大三通 \t \n8\t\n2023/10/29-2023/11/4\n\tECFA \t \n9\t\n2023/11/5 -2023/11/11\n\t期中考 \t \n10\t\n2023/11/12-2023/11/18\n\t金廈自由行 \t \n11\t\n2023/11/19-2023/11/25\n\t金廈自由行 \t \n12\t\n2023/11/26-2023/12/2\n\t博奕娛樂事業概論 \t \n13\t\n2023/12/3 -2023/12/9\n\t專題報告 \t \n14\t\n2023/12/10-2023/12/16\n\t專題報告 \t \n15\t\n2023/12/17-2023/12/23\n\t專題報告 \t \n16\t\n2023/12/24-2023/12/30\n\t專題報告 \t \n17\t\n2023/12/31-2024/1/6 0\n\t專題報告 \t \n18\t\n2024/1/7 0-2024/1/13\n\t期末考 \t \n\n\n6.成績評定及課堂要求\n期中考30%、期末考40%、平日出勤30% \n專心聽課、禁滑手機 \n \n\n\n8.永續發展目標(SDGs)：\n\n\n9.大學社會責任(USR)關聯性："
}