{
    "semester": "113-2",
    "list_info": {
        "部別": "日間部學士班",
        "科系": "電機工程學系",
        "班級": "電機三甲",
        "選課代碼": "0079",
        "科目名稱": "前瞻性類比積體電路佈局設計",
        "科目英文名": "Advanced Analog IC Layout Design and Laboratory",
        "學分": "3.0",
        "時數": "3.0",
        "必/選": "選修",
        "授課教師": "陳俊達",
        "教室": "E223軟體與模擬實驗室",
        "修課人數": "40",
        "上限人數": "45",
        "上課時間": "(三)2-4",
        "限修備註": "",
        "備註": ""
    },
    "detail_raw_text": "回上一頁\t國立金門大學\t \n \t教學綱要\t \n\n部別 : 日間部學士班\t113學年度第2學期\t列印日期 : 2026/05/24\n科目名稱 : 前瞻性類比積體電路佈局設計 (Advanced Analog IC Layout Design and Laboratory)\t開課班級 : 電機三甲\t學　　分 : 3.0\t授課時數 : 3.0\n授課教師 : 陳俊達\t必選修 : 選修\t \t \n\n\n1.教學目標\n近來，台灣的半導體產業迅速成長，所以積體電路的設計人才的培養，需在學校紮下根基，相關EDA工具大廠的佈局軟體，從電路圖設計、電路分析模擬到電路佈局環境一應俱全。使學生瞭解積體電路設計工作環境及軟體功能。 \n\n\n2.教學綱要\n1.Differences between layout and circuit\n2.R、C layout\n3.Analog cell layout\n4.Current mirror layout\n5.OP layout\n6.LNA layout \n\n\n3.教科書\n3\t書名 : 類比積體電路佈局　\n出版日期 : 年 月 \n作者 : 廖裕評、陸瑞強　出版社 : 全華書局　版本 :  \n\n\n4.參考書\n1\t書名 : 電路設計模擬　出版日期 : 年 月 \n作者 : 盧勤庸　出版社 : 全華圖書　版本 :  \n2\t書名 : 電腦輔助電路設計　出版日期 : 年 月 \n作者 : 陳淳杰　出版社 : 全華圖書　版本 :  \n3\t書名 : SPICE電子電路模擬　出版日期 : 年 月 \n作者 : 張文清　出版社 : 鼎茂　版本 :  \n4\t書名 : 電路程式：OrCAD PSpice 16.X　出版日期 : 年 月 \n作者 : 鄭光欽　出版社 : 高立圖書　版本 :  \n5\t書名 : CMOS電路模擬與設計　出版日期 : 年 月 \n作者 : 鍾文耀、鄭美珠　出版社 : 全華圖書　版本 :  \n\n※請遵守智慧財產權觀念，依著作權法規定，教科書及教材不得非法影印與使用盜版軟體。\n\n5.教學進度表\n週次\t日期\t內容\t備註\n1\t\n2025/02/16─2025/02/22\n\t工程專業倫理\nDifferences between layout and circuit \t \n2\t\n2025/02/23─2025/03/01\n\tCMOS layout style\n \t \n3\t\n2025/03/02─2025/03/08\n\tcmos layout \t \n4\t\n2025/03/09─2025/03/15\n\tcmos layout \t \n5\t\n2025/03/16─2025/03/22\n\tAnalog cell layout \t \n6\t\n2025/03/23─2025/03/29\n\tAnalog cell layout \t \n7\t\n2025/03/30─2025/04/05\n\tAnalog floor plan  \t \n8\t\n2025/04/06─2025/04/12\n\tI/O pad layout issue \t \n9\t\n2025/04/13─2025/04/19\n\t期中考 \t \n10\t\n2025/04/20─2025/04/26\n\tI/O pad layout issue \t \n11\t\n2025/04/27─2025/05/03\n\tresistance layout \t \n12\t\n2025/05/04─2025/05/10\n\tcapacitance layout \t \n13\t\n2025/05/11─2025/05/17\n\tinductance layout \t \n14\t\n2025/05/18─2025/05/24\n\tCurrent mirror layout \t \n15\t\n2025/05/25─2025/05/31\n\tCurrent mirror layout \t \n16\t\n2025/06/01─2025/06/07\n\tBJT layout \t \n17\t\n2025/06/08─2025/06/14\n\t線上學習 \t \n18\t\n2025/06/15─2025/06/21\n\t線上學習 \t \n\n\n6.成績評定及課堂要求\n考試20%;作業70%;出席10% \n \n \n\n\n8.永續發展目標(SDGs)：\n\n\n9.大學社會責任(USR)關聯性："
}