{
    "semester": "114-1",
    "list_info": {
        "部別": "日間部學士班",
        "科系": "國際暨大陸事務學系",
        "班級": "國際一",
        "選課代碼": "0258",
        "科目名稱": "近代外交史(一)",
        "科目英文名": "Modern Diplomatic HistoryⅠ",
        "學分": "2.0",
        "時數": "2.0",
        "必/選": "必修",
        "授課教師": "陳慧菁",
        "教室": "123黃木榮講堂",
        "修課人數": "24",
        "上限人數": "60",
        "上課時間": "(五)5-6",
        "限修備註": "",
        "備註": ""
    },
    "detail_raw_text": "回上一頁\t國立金門大學\t \n \t教學綱要\t \n\n部別 : 日間部學士班\t114學年度第1學期\t列印日期 : 2026/05/24\n科目名稱 : 近代外交史(一) (Modern Diplomatic HistoryⅠ)\t開課班級 : 國際一\t學　　分 : 2.0\t授課時數 : 2.0\n授課教師 : 陳慧菁\t必選修 : 必修\t \t \n\n\n1.教學目標\n課程以西洋近代史為主要課程講授範圍。以西伐利亞條約體系後，近代民族國家體系之建立，探討西方民族國家的政治的互動發展與模式建立。課程藉由近代國際關係的歷史，包含國際體系的演進、戰爭與衝突、權力發展等概念，對於國際關係的發展歷程進行介紹。希望在課程中分析國際關係形塑的背景，協助修課同學建構完整近代史觀，以對於近代史的基礎知識之建立有所助益。 \n\n\n2.教學綱要\n本學期課程共分四個階段：近代國際體系的建立與概述進行介紹、1815-1914年近代外交史之發展、1914-1945年19世紀初期西方外交事件與模式建構、1945-2001年第二次世界大戰結束後國際體系的建立與發展。 \n\n\n3.教科書\n1\t書名 : 近代國際關係史　\n出版日期 : 年 月 \n作者 : 張麟徵　出版社 : 揚智文化　版本 :  \n2\t書名 : 西洋外交史　\n出版日期 : 年 月 \n作者 : 蔡東杰　出版社 : 風雲論壇　版本 :  \n4\t書名 : 中國外交史新論　\n出版日期 : 年 月 \n作者 : 蔡東杰　出版社 : 風雲論壇　版本 :  \n5\t書名 : 中國外交史要義　\n出版日期 : 年 月 \n作者 : 王增才　出版社 : 五南　版本 :  \n\n\n4.參考書\n1\t書名 : 西洋近代史　出版日期 : 年 月 \n作者 : 王增才　出版社 : 正中　版本 :  \n\n※請遵守智慧財產權觀念，依著作權法規定，教科書及教材不得非法影印與使用盜版軟體。\n\n5.教學進度表\n週次\t日期\t內容\t備註\n1\t\n2025/09/14─2025/09/20\n\t課程說明與前測 \t \n2\t\n2025/09/21─2025/09/27\n\t課程導論：近代國際體系的演進 \t \n3\t\n2025/09/28─2025/10/04\n\t拿破崙戰爭 \t \n4\t\n2025/10/05─2025/10/11\n\t維也納會議 \t \n5\t\n2025/10/12─2025/10/18\n\t歐洲協商制度 \t \n6\t\n2025/10/19─2025/10/25\n\t門羅主義 \t \n7\t\n2025/10/26─2025/11/01\n\t歐洲革命騷動：1830年革命 \t \n8\t\n2025/11/02─2025/11/08\n\t列強的變化：1848年革命 \t \n9\t\n2025/11/09─2025/11/15\n\t期中考 \t \n10\t\n2025/11/16─2025/11/22\n\t英國的霸權 \t \n11\t\n2025/11/23─2025/11/29\n\t克里米亞戰爭與影響 \t \n12\t\n2025/11/30─2025/12/06\n\t義大利的統合 \t \n13\t\n2025/12/07─2025/12/13\n\t德意志的統一 \t \n14\t\n2025/12/14─2025/12/20\n\t歐洲體系的改變 \t \n15\t\n2025/12/21─2025/12/27\n\t俾斯麥體系 \t \n16\t\n2025/12/28─2026/01/03\n\t期末考試 \t \n17\t\n2026/01/04─2026/01/10\n\t指定閱讀 \t \n18\t\n2026/01/11─2026/01/17\n\t指定閱讀 \t \n\n\n6.成績評定及課堂要求\n1.課堂參與(出席與發問、報告)佔40%： （1）每週出席成績佔10%。 （2）某週課堂小考與作業單佔30%，作為平時成績的評量。小考與作業單若未參與者，將喪失此項成績。 2.期中考試佔30%。 3.期末報告佔30% ※教師得視學習成效，不定時就課程範圍進行課堂作業指定，作為調整分數之依據。  \n1.每學期缺席(包含請假)次數不可超過4次。 2.需參與課堂討論與問題回答。 \n \n\n\n8.永續發展目標(SDGs)：SDG16 和平、正義及健全制度\n\n\n9.大學社會責任(USR)關聯性：中"
}