{
    "semester": "114-1",
    "list_info": {
        "部別": "日間部學士班",
        "科系": "都市計畫與景觀學系",
        "班級": "都景二",
        "選課代碼": "0381",
        "科目名稱": "環境行為學",
        "科目英文名": "Environment and Behavior",
        "學分": "2.0",
        "時數": "2.0",
        "必/選": "選修",
        "授課教師": "黃文華",
        "教室": "515專業教室",
        "修課人數": "27",
        "上限人數": "60",
        "上課時間": "(三)10-11",
        "限修備註": "",
        "備註": ""
    },
    "detail_raw_text": "回上一頁\t國立金門大學\t \n \t教學綱要\t \n\n部別 : 日間部學士班\t114學年度第1學期\t列印日期 : 2026/05/24\n科目名稱 : 環境行為學 (Environment and Behavior)\t開課班級 : 都景二\t學　　分 : 2.0\t授課時數 : 2.0\n授課教師 : 黃文華\t必選修 : 選修\t \t \n\n\n1.教學目標\n(1)理解人與環境之間的相互關係。 (2)掌握環境行為學的調查研究方法。 (3)了解當前與未來的環境挑戰。 (4)結合環境行為學專業知識進行規劃與設計。 (5)強化永續性為主的規劃設計意識。 \n\n\n2.教學綱要\n(1)認識環境行為學的起源與發展脈絡。\n(2)了解環境行為學的研究理論框架。\n(3)了解環境行為學應用與研究趨勢。\n(4)應用環境行為學的調查研究方法。\n(5)評論環境行為學重要研究文章與研究個案。 \n\n\n3.教科書\n1\t書名 : 李增道(1999)。環境行為學概論。北京：清華大學出版社　\n出版日期 : 年 月 \n作者 : 　出版社 : 　版本 :  \n2\t書名 : 胡正凡、林玉蓮(2018)。環境心理學：環境-行為硏究及其設計應用。北京：中國建築工業出版社。　\n出版日期 : 年 月 \n作者 : 　出版社 : 　版本 :  \n3\t書名 : 徐偉(2021)。環境行為學。北京：中國建築工業出版社。　\n出版日期 : 年 月 \n作者 : 　出版社 : 　版本 :  \n4\t書名 : 徐磊青、楊公俠(2021)。環境心理學－環境、知覺和行為。台北：五南圖書。　\n出版日期 : 年 月 \n作者 : 　出版社 : 　版本 :  \n5\t書名 : 常懷生(1999)。建築環境心理學。台北：田園城市文化。　\n出版日期 : 年 月 \n作者 : 　出版社 : 　版本 :  \n7\t書名 : Zeisel, J.(著), 關華山(譯)(1996)。研究與設計《Inquiry by desig\nn : environment/behavior/neuroscience in architect\nure, interiors, landscape, and planning》。台北：田園城市文化\n。　\n出版日期 : 年 月 \n作者 : 　出版社 : 　版本 :  \n8\t書名 : Lynch, K(著), 胡家璇(譯)(2014)。城市的意象《The Image of the C\nity》。台北：遠流。　\n出版日期 : 年 月 \n作者 : 　出版社 : 　版本 :  \n9\t書名 : McAndrew, F.T.(著), 危芷芬（譯）(2023)。環境心理學《Environmenta\nl Psychology》。台北：五南圖書。　\n出版日期 : 年 月 \n作者 : 　出版社 : 　版本 :  \n\n\n4.參考書\n1\t書名 : Franck, K. A. (1984). Exorcising the ghost of physical determinism. Environment and Behavior, 16(4), 411–435. https://doi.org/10.1177/0013916584164001　出版日期 : 年 月 \n作者 : 　出版社 : 　版本 :  \n2\t書名 : Giuliani, MV, Scopelliti M. (2009). Empirical research in environmental psychology: past, present, and future. Journal of Environmental Psychology, 29:375–86　出版日期 : 年 月 \n作者 : 　出版社 : 　版本 :  \n3\t書名 : Gobster, P.H., Palmer, J.F., Crystal, J.H., & Ervin H.Z.(2003).The significance and impact his contributions to environment-behavior studies. Environment and Behavior, 35(2):165-186　出版日期 : 年 月 \n作者 : 　出版社 : 　版本 :  \n4\t書名 : Milfont, T. L., Page E. (2013). A bibliometric review of the first thirty years of the Journal of Environmental Psychology. Psyecology, 4, 195–216.　出版日期 : 年 月 \n作者 : 　出版社 : 　版本 :  \n5\t書名 : Milfont, T. L., Amirbagheri, K., Hermanns, E., & Merigó, J. M. (2019). Celebrating Half a Century of Environment and Behavior: A Bibliometric Review. Environment and Behavior, 51(5), 469-501. https://doi.org/10.1177/0013916519843126　出版日期 : 年 月 \n作者 : 　出版社 : 　版本 :  \n6\t書名 : Rapoport, A. (2008). “Environment-Behavior Studies: Past, Present, and Future.” Journal of Architectural and Planning Research, 25 (4): 276–281.　出版日期 : 年 月 \n作者 : 　出版社 : 　版本 :  \n7\t書名 : Rappoport, A. (1999). A framework for studying vernacular design. Journal of Architectural and Planning Research, 16(1): 52-64.　出版日期 : 年 月 \n作者 : 　出版社 : 　版本 :  \n8\t書名 : Scott, M. M. (2005). A powerful theory and a paradox: Ecological psychologists after Barker. Environment and Behavior, 37, 295–329.　出版日期 : 年 月 \n作者 : 　出版社 : 　版本 :  \n9\t書名 : Tam, K.-P., & Milfont, T. L. (2020). Towards cross-cultural environmental psychology: A state-of-the-art review and recommendations. Journal of Environmental Psychology, 71, 101474. https://doi.org/10.1016/j.jenvp.2020.101474　　出版日期 : 年 月 \n作者 : 　出版社 : 　版本 :  \n10\t書名 : Wapner, S., Demick, J., Yamamoto, T., & Minami, H. (Eds.). (2000). Theoretical perspectives in environment-behavior research: Underlying assumptions, research problems, and methodologies. Kluwer Academic Publishers. https://doi.org/10.1007/978-1-4615-4701-3　出版日期 : 年 月 \n作者 : 　出版社 : 　版本 :  \n11\t書名 : Zeisel, J. (2006). Inquiry by design: Environment/behavior/neuroscience in architecture, interiors, landscape, and planning. W W Norton & Co.　出版日期 : 年 月 \n作者 : 　出版社 : 　版本 :  \n\n※請遵守智慧財產權觀念，依著作權法規定，教科書及教材不得非法影印與使用盜版軟體。\n\n5.教學進度表\n週次\t日期\t內容\t備註\n1\t\n2025/09/14─2025/09/20\n\t課程說明 \t\n1.環境行為學的起源與發展脈絡\n2.環境行為學VS環境心理學 \n2\t\n2025/09/21─2025/09/27\n\t環境行為學重要研究人員與理論引介 \t1.Roger Barker: Ecological Psychology\n2.Edward T. Hall: Proxemics\n3.Robert Sommer: Personal Space\n4.Kevin Lynch: Environmental Image\n5.Christopher Alexander: Pattern Language \n3\t\n2025/09/28─2025/10/04\n\t研究與設計的重新思考 \t\n對於規劃人才研究設計思路為何--環境行為學的取徑思考 \n4\t\n2025/10/05─2025/10/11\n\t環境認知與空間(一) \t\n1.環境覺知\n2.空間認知 \n5\t\n2025/10/12─2025/10/18\n\t環境認知與空間(二) \t\n1.城市意象\n2.找路與認知距離 \n6\t\n2025/10/19─2025/10/25\n\t空間行為(一) \t\n1.個人空間\n2.私密性 \n7\t\n2025/10/26─2025/11/01\n\t空間行為(二)\n \t\n1.領域性\n2.擁擠 \n8\t\n2025/11/02─2025/11/08\n\t行為場景與場所依戀 \t \n9\t\n2025/11/09─2025/11/15\n\t期中報告 \t \n10\t\n2025/11/16─2025/11/22\n\t環境評價 \t\n1.景觀評價\n2.用後評估(POE) \n11\t\n2025/11/23─2025/11/29\n\t環境壓力與行為調適 \t\n1.潛在環境的特殊性\n2.環境負荷\n3.壓力的性質與過程\n4.塗鴉空間與行為 \n12\t\n2025/11/30─2025/12/06\n\t工作環境與行為 \t\n1.房間與家具\n2.物理環境與工作表現\n3.特定工作環境 \n13\t\n2025/12/07─2025/12/13\n\t學習環境與行為 \t\n1.校園環境載體特性\n2.學校與社區\n3.博物館與地方 \n14\t\n2025/12/14─2025/12/20\n\t居住環境與行為 \t\n1.場所、所在、地方、空間、領域等概念釐清\n2.地方感(SOP)\n3.老人學(Gerontology)取徑的環境行為學 \n15\t\n2025/12/21─2025/12/27\n\t*自然環境與行為\n*環境行為學的重要研究趨勢與未來發展前沿\n \t1.自然與環境兩個概念釐清\n2.環境問題與負責任的環境行為\n3.自然療癒\n \n16\t\n2025/12/28─2026/01/03\n\t期末考 \t \n17\t\n2026/01/04─2026/01/10\n\t彈性授課-環境行為學議題討論(一) \t \n18\t\n2026/01/11─2026/01/17\n\t彈性授課-環境行為學議題討論(二) \t \n\n\n6.成績評定及課堂要求\n*出席及上課參與30%。 *期中報告30%。 *期末考40% 。  \n*對未來的最好準備，就是充分利用當下的每一分鐘，請各位同學上課準時。 \n \n\n\n8.永續發展目標(SDGs)：SDG10 減少不平等、SDG11 永續城鄉\n\n\n9.大學社會責任(USR)關聯性：中"
}