{
    "semester": "113-1",
    "list_info": {
        "部別": "日間部學士班",
        "科系": "應用英語學系",
        "班級": "應英一年級",
        "選課代碼": "0338",
        "科目名稱": "簡報技巧",
        "科目英文名": "Presentation Skills",
        "學分": "2.0",
        "時數": "2.0",
        "必/選": "選修",
        "授課教師": "羅主恩",
        "教室": "430普通教室",
        "修課人數": "19",
        "上限人數": "60",
        "上課時間": "(五)3-4",
        "限修備註": "",
        "備註": ""
    },
    "detail_raw_text": "回上一頁\t國立金門大學\t \n \t教學綱要\t \n\n部別 : 日間部學士班\t113學年度第1學期\t列印日期 : 2026/05/24\n科目名稱 : 簡報技巧 (Presentation Skills)\t開課班級 : 應英一年級\t學　　分 : 2.0\t授課時數 : 2.0\n授課教師 : 羅主恩\t必選修 : 選修\t \t \n\n\n1.教學目標\nCourse Description: The aim of this course is to provide students with the necessary skills, techniques and methods to be effective in presenting in front of an audience. In addition to this, the course helps participants streamline and improve their performance through the observation and analysis of their own presentations and those of others. Promote further development of communication skills, quantitative analysis, critical thinking, and methods of presenting varying levels of technological information. The course focus will be the close examination of the elements that characterize an efficient, thorough, clear and effective presentation. Equal emphasis will be on the extensive building of vocabulary. \n\n\n2.教學綱要\nObjectives: Students will:\n1. develop the ability to read critically and recognize the qualities of technical and scientific writings;\n2. examine the elements of a quality oral presentation by:\na. describing and analyzing the structure of an oral presentation;\nb. determine what background information, if any, should be included;\nc. determine the visual aids that would enhance the presentation;\n\nActivities: Selected readings will be summarized and discussed for content, adding, and interpreting technical terminology, concepts, and methodology. Students will be required to research topic and determine what background information is needed for better understanding both for the speaker as well as the audience. Students will develop group presentations during the course of the semester. A written presentation will be required in addition to an outline. Visual materials will be a part of the assignment grade.\n \n\n\n3.教科書\n1\t書名 : Presentations in English.　\n出版日期 : 2008年 月 \n作者 : Williams, Erica J.　出版社 : Oxford: Macmillan,　版本 :  \n\n\n4.參考書\n1\t書名 : online resources　出版日期 : 年 月 \n作者 : 　出版社 : 　版本 :  \n\n※請遵守智慧財產權觀念，依著作權法規定，教科書及教材不得非法影印與使用盜版軟體。\n\n5.教學進度表\n週次\t日期\t內容\t備註\n1\t\n2024/09/08─2024/09/14\n\tIntroduction to class. Step 1 \t \n2\t\n2024/09/15─2024/09/21\n\tStep 1 \t \n3\t\n2024/09/22─2024/09/28\n\tStep 1, Step 2 \t \n4\t\n2024/09/29─2024/10/05\n\tStep 2 \t \n5\t\n2024/10/06─2024/10/12\n\tStep 2, Step 3 \t \n6\t\n2024/10/13─2024/10/19\n\tStep 3 \t \n7\t\n2024/10/20─2024/10/26\n\tStep 3, Step 4 \t \n8\t\n2024/10/27─2024/11/02\n\tStep 4 Group Presentations \t \n9\t\n2024/11/03─2024/11/09\n\tGroup Presentations, Review For Midterm \t \n10\t\n2024/11/10─2024/11/16\n\tWritten Midterm Exam, good luck! \t \n11\t\n2024/11/17─2024/11/23\n\tGroup presentations, Step 5 \t \n12\t\n2024/11/24─2024/11/30\n\tStep 5, Step 6 \t \n13\t\n2024/12/01─2024/12/07\n\tStep 6 \t \n14\t\n2024/12/08─2024/12/14\n\tStep 6, 7 \t \n15\t\n2024/12/15─2024/12/21\n\tGroup Presentations, Step 7 \t \n16\t\n2024/12/22─2024/12/28\n\tGroup Presentations, Step 7 \t \n17\t\n2024/12/29─2025/01/04\n\tIndependent Study \t \n18\t\n2025/01/05─2025/01/11\n\tIndividual Conference \t \n\n\n6.成績評定及課堂要求\nEvaluation: 30%-mid-term examination; 30%-final examination; class participation 40% (Attendance, tardiness, participation in class discussions and group oral reports, quizzes). \nRequirements: 1. Attendance, punctuality. Quizzes, other assignments. 2. Group presentations (10 -12 minutes) 3. ALL presentations and assignments are due on the specified date. Points will be deducted for late work. No late presentations will be permitted. 4. The Midterm Exam will be a written test that will cover Steps 1 through 4 in the textbook. The Final Exam will be accumulative, but will have fewer questions from the first half of the book.  \n \n\n\n8.永續發展目標(SDGs)：\n\n\n9.大學社會責任(USR)關聯性："
}