{
    "semester": "113-2",
    "list_info": {
        "部別": "日間部學士班",
        "科系": "華語文學系",
        "班級": "華文二",
        "選課代碼": "0365",
        "科目名稱": "當代文藝思潮",
        "科目英文名": "Contemporary Literary Trends",
        "學分": "2.0",
        "時數": "2.0",
        "必/選": "必修",
        "授課教師": "侯建州",
        "教室": "421方水金講堂",
        "修課人數": "20",
        "上限人數": "60",
        "上課時間": "(二)3-4",
        "限修備註": "",
        "備註": ""
    },
    "detail_raw_text": "回上一頁\t國立金門大學\t \n \t教學綱要\t \n\n部別 : 日間部學士班\t113學年度第2學期\t列印日期 : 2026/05/24\n科目名稱 : 當代文藝思潮 (Contemporary Literary Trends)\t開課班級 : 華文二\t學　　分 : 2.0\t授課時數 : 2.0\n授課教師 : 侯建州\t必選修 : 必修\t \t \n\n\n1.教學目標\n以當代議題為核心，選擇當代重要文藝思潮與理論，帶領同學研讀文本，賞析現當代文藝創作，認識當前社會潮流，同時培養鑑賞能力。 \n\n\n2.教學綱要\n一、瞭解當代文藝思潮的內涵\n二、當代文藝創作與展覽欣賞\n三、多元文藝創作的概念與成品\n四、文藝場域的生成與結構\n \n\n\n3.教科書\n1\t書名 : 自編講義　\n出版日期 : 年 月 \n作者 : 　出版社 : 　版本 :  \n\n\n4.參考書\n1\t書名 : 視覺與認同　出版日期 : 年 月 \n作者 : 史書美　出版社 : 　版本 :  \n2\t書名 : 反離散:華語語系研究論　出版日期 : 年 月 \n作者 : 史書美　出版社 : 　版本 :  \n3\t書名 : 　出版日期 : 年 月 \n作者 : 　出版社 : 　版本 :  \n\n※請遵守智慧財產權觀念，依著作權法規定，教科書及教材不得非法影印與使用盜版軟體。\n\n5.教學進度表\n週次\t日期\t內容\t備註\n1\t\n2025/02/16─2025/02/22\n\t課程介紹與討論 \t \n2\t\n2025/02/23─2025/03/01\n\t全球資本主義下的視覺與認同 \t \n3\t\n2025/03/02─2025/03/08\n\t全球資本主義下的視覺與認同 \t \n4\t\n2025/03/09─2025/03/15\n\t全球資本主義下的視覺與認同 \t全球化與弱裔化 \n5\t\n2025/03/16─2025/03/22\n\t女性主義的跨國性 \t \n6\t\n2025/03/23─2025/03/29\n\t女性主義的跨國性 \t \n7\t\n2025/03/30─2025/04/05\n\t慾望的地緣政治 \t \n8\t\n2025/04/06─2025/04/12\n\t慾望的地緣政治 \t \n9\t\n2025/04/13─2025/04/19\n\t期中評量 \t \n10\t\n2025/04/20─2025/04/26\n\t曖昧的身分認同 \t \n11\t\n2025/04/27─2025/05/03\n\t曖昧的身分認同 \t \n12\t\n2025/05/04─2025/05/10\n\t國族寓言之後 \t \n13\t\n2025/05/11─2025/05/17\n\t國族寓言之後 \t \n14\t\n2025/05/18─2025/05/24\n\t帝國夾縫間的世界主義 \t \n15\t\n2025/05/25─2025/05/31\n\t華語語系的時間與地方 \t \n16\t\n2025/06/01─2025/06/07\n\t期末評量 \t \n17\t\n2025/06/08─2025/06/14\n\t彈性課程 \t \n18\t\n2025/06/15─2025/06/21\n\t彈性課程 \t \n\n\n6.成績評定及課堂要求\n課堂出席、參與討論：60%　 　　　　　　 期中測驗(或報告)、期末考核(或報告)：共佔40%  \n遵守教師規定，積極參與討論，盡力完成報告與作業  \n教師將視實際需求予以調整，切勿任意缺課，請假須經正式核准。 \n\n\n8.永續發展目標(SDGs)：SDG4 優質教育、SDG16 和平、正義及健全制度\n\n\n9.大學社會責任(USR)關聯性：中"
}