{
    "semester": "112-2",
    "list_info": {
        "部別": "日間部學士班",
        "科系": "食品科學系",
        "班級": "食品一",
        "選課代碼": "0100",
        "科目名稱": "生物統計實習",
        "科目英文名": "Biostatistics Experiment",
        "學分": "1.0",
        "時數": "3.0",
        "必/選": "必修",
        "授課教師": "吳尹文",
        "教室": "I101圖資電腦教室",
        "修課人數": "38",
        "上限人數": "60",
        "上課時間": "(五)5-7",
        "限修備註": "",
        "備註": ""
    },
    "detail_raw_text": "回上一頁\t國立金門大學\t \n \t教學綱要\t \n\n部別 : 日間部學士班\t112學年度第2學期\t列印日期 : 2026/05/24\n科目名稱 : 生物統計實習 (Biostatistics Experiment)\t開課班級 : 食品一\t學　　分 : 1.0\t授課時數 : 3.0\n授課教師 : 吳尹文\t必選修 : 必修\t \t \n\n\n1.教學目標\n讓同學對於生物統計有基本概念，並讓其熟習Excel軟體之操作，利用設計問卷及收集問卷數據，學習資料的整理與不同統計檢定方式，作為往後資料處理分析之基礎 \n\n\n2.教學綱要\n先介紹Excel 軟體基本操作，再藉由設計問卷、問卷訪視、資料收集及資料分析過程，熟悉統計分析應用之步驟。 \n\n\n3.教科書\n1\t書名 : 自編教材　\n出版日期 : 年 月 \n作者 : 　出版社 : 　版本 :  \n\n\n無參考書資料。\n\n※請遵守智慧財產權觀念，依著作權法規定，教科書及教材不得非法影印與使用盜版軟體。\n\n5.教學進度表\n週次\t日期\t內容\t備註\n1\t\n2024/02/18─2024/02/24\n\t課程介紹、分組 \t \n2\t\n2024/02/25─2024/03/02\n\t問卷設計、編碼與資料驗證 \t \n3\t\n2024/03/03─2024/03/09\n\t資料整理與表現 – 統計表與統計圖(1) \t \n4\t\n2024/03/10─2024/03/16\n\t資料整理與表現 – 統計測量數(1) \t \n5\t\n2024/03/17─2024/03/23\n\t資料整理與表現 – 統計測量數(2) \t \n6\t\n2024/03/24─2024/03/30\n\t問卷設計及檢討 \t \n7\t\n2024/03/31─2024/04/06\n\t統計估計(1) \t \n8\t\n2024/04/07─2024/04/13\n\t統計估計(2) \t \n9\t\n2024/04/14─2024/04/20\n\t期中考 \t \n10\t\n2024/04/21─2024/04/27\n\t假設檢定(1) \t \n11\t\n2024/04/28─2024/05/04\n\t假設檢定(2) \t \n12\t\n2024/05/05─2024/05/11\n\t簡單迴歸分析與相關分析 \t \n13\t\n2024/05/12─2024/05/18\n\t平均數比較(t檢定、單因子變異數分析) \t \n14\t\n2024/05/19─2024/05/25\n\t分組報告(1) \t \n15\t\n2024/05/26─2024/06/01\n\t分組報告(2) \t \n16\t\n2024/06/02─2024/06/08\n\t分組報告(3) \t \n17\t\n2024/06/09─2024/06/15\n\t課程複習與討論 \t \n18\t\n2024/06/16─2024/06/22\n\t期末考 \t \n\n\n6.成績評定及課堂要求\n1.平時成績　　佔60% (含課堂表現、分組報告及出缺席) 2.期中考 　佔20% 3.期末考 佔20% \n1.需分組進行設計問卷、問卷訪視、資料收集及資料分析，最後統整並分組報告 2.期中考及期末考須依座位表就坐，請提早5-10分鐘至考場 3.攜帶學生證或證明文件(未攜帶者扣該科該次成績10分) 4.考試時間為1小時，遲到15分鐘者不得應考；20分鐘後即可交卷 5.請利用藍色或黑色原子筆或鋼筆書寫，不可用鉛筆作答 6.補考(最高分為59分；低於59分者以59分計算) \n一、分組報告規則： 1.穿著正式服裝 2.按照順序報告(排時間) 3.需製作ppt檔 4.報告時間為15分鐘；第12分鐘響鈴第一次；第15分鐘再次響鈴第二次 二、書面規則： 1.需加封面 2.字型及大小統一 3.格式需符合格式 4.規定時間內繳交 \n\n\n8.永續發展目標(SDGs)：\n\n\n9.大學社會責任(USR)關聯性："
}