{
    "semester": "114-2",
    "list_info": {
        "部別": "日間部研究所碩士班",
        "科系": "土木與工程管理學系",
        "班級": "土木碩一",
        "選課代碼": "0179",
        "科目名稱": "航空攝影測量",
        "科目英文名": "Photogrammetry",
        "學分": "3.0",
        "時數": "3.0",
        "必/選": "選修",
        "授課教師": "吳宗江",
        "教室": "E105教室(理工大樓)",
        "修課人數": "7",
        "上限人數": "30",
        "上課時間": "(四)2-4",
        "限修備註": "",
        "備註": ""
    },
    "detail_raw_text": "回上一頁\t國立金門大學\t \n \t教學綱要\t \n\n部別 : 日間部研究所碩士班\t114學年度第2學期\t列印日期 : 2026/05/24\n科目名稱 : 航空攝影測量 (Photogrammetry)\t開課班級 : 土木碩一\t學　　分 : 3.0\t授課時數 : 3.0\n授課教師 : 吳宗江\t必選修 : 選修\t \t \n\n\n1.教學目標\n航空攝影測量學技術所建置的圖資及其後續工程應用是工程界不可或缺的需求與專業知識，使本系學生具有航空攝影測量的專業知識並及結合工程應用之能力，同時培養整合無人飛行載具(UAV)之創新應用思維，此為本課程之教學目標。 \n\n\n2.教學綱要\n1. 航空攝影測量學基礎理論\n2. 航空攝影測量學技術應用\n3. 航空攝影測量學創新整合\n \n\n\n3.教科書\n1\t書名 : 航空攝影測量學　\n出版日期 : 年 月 \n作者 : 何維信　出版社 : 大中國圖書公司　版本 :  \n\n\n4.參考書\n1\t書名 : Introduction to Modern Photogrammetry　出版日期 : 年 月 \n作者 : Edward M. Mikhail, James S. Bethel, J. Chris McGlone,　出版社 : 　版本 :  \n\n※請遵守智慧財產權觀念，依著作權法規定，教科書及教材不得非法影印與使用盜版軟體。\n\n5.教學進度表\n週次\t日期\t內容\t備註\n1\t\n2026/02/22─2026/02/28\n\t緒論 \t \n2\t\n2026/03/01─2026/03/07\n\t攝影測量之基本光學 \t \n3\t\n2026/03/08─2026/03/14\n\t像片及其他感應之處理 \t \n4\t\n2026/03/15─2026/03/21\n\t攝影測量之攝影機與成像系統 \t \n5\t\n2026/03/22─2026/03/28\n\t立體觀察與視差 \t \n6\t\n2026/03/29─2026/04/04\n\t像片之基本幾何性質 \t \n7\t\n2026/04/05─2026/04/11\n\t簡易攝影測量之作業 \t \n8\t\n2026/04/12─2026/04/18\n\t期中考試 \t \n9\t\n2026/04/19─2026/04/25\n\t像片之量測與化算 \t \n10\t\n2026/04/26─2026/05/02\n\t單張像片之空間後方交會糾正 \t \n11\t\n2026/05/03─2026/05/09\n\t方位判定之理論與技術 \t \n12\t\n2026/05/10─2026/05/16\n\t立體測圖儀 \t \n13\t\n2026/05/17─2026/05/23\n\t攝影空中三角測量 \t \n14\t\n2026/05/24─2026/05/30\n\t正射像片 \t \n15\t\n2026/05/31─2026/06/06\n\t攝影測量計畫之規劃 \t \n16\t\n2026/06/07─2026/06/13\n\t期末考 \t \n17\t\n2026/06/14─2026/06/20\n\t專題製作(1) \t \n18\t\n2026/06/21─2026/06/27\n\t專題製作(2) \t \n\n\n6.成績評定及課堂要求\n期中考30%，期末考30%，平時成績40% \n尊重學習權益 \n \n\n\n8.永續發展目標(SDGs)：SDG9 工業化、創新及基礎建設、SDG11 永續城鄉\n\n\n9.大學社會責任(USR)關聯性：高"
}