{
    "semester": "114-1",
    "list_info": {
        "部別": "日間部學士班",
        "科系": "運動與休閒學系",
        "班級": "運休四",
        "選課代碼": "0626",
        "科目名稱": "休閒治療",
        "科目英文名": "Leisure Therapy",
        "學分": "2.0",
        "時數": "2.0",
        "必/選": "選修",
        "授課教師": "毛彥明",
        "教室": "129運休系普通教室",
        "修課人數": "25",
        "上限人數": "60",
        "上課時間": "(五)5-6",
        "限修備註": "",
        "備註": ""
    },
    "detail_raw_text": "回上一頁\t國立金門大學\t \n \t教學綱要\t \n\n部別 : 日間部學士班\t114學年度第1學期\t列印日期 : 2026/05/24\n科目名稱 : 休閒治療 (Leisure Therapy)\t開課班級 : 運休四\t學　　分 : 2.0\t授課時數 : 2.0\n授課教師 : 毛彥明\t必選修 : 選修\t \t \n\n\n1.教學目標\n了解與認識休閒治療的涵蓋範圍、特性、應用範疇與重要性，以及休閒治療所需注意事項。進而討論休閒治療的核心觀念、應用領域，並模擬設計休閒治療之內容。 \n\n\n2.教學綱要\n介紹休閒治療的理論、組織及該專業領域的形成，討論休閒治療在各領域的應用或對各種疾病的幫助，例如對老年人及幼童的幫助方式、對自閉症或神經肌肉病變等疾病改善之重要性。 \n\n\n3.教科書\n2\t書名 : 治療式遊憩導論　\n出版日期 : 2007年 10月 \n作者 : David R. Austin, Michael E. Crawford　出版社 : 品度股份有限公司　版本 : 初版 \n\n\n無參考書資料。\n\n※請遵守智慧財產權觀念，依著作權法規定，教科書及教材不得非法影印與使用盜版軟體。\n\n5.教學進度表\n週次\t日期\t內容\t備註\n1\t\n2025/09/14─2025/09/20\n\t休閒治療的緒論與導覽 \t \n2\t\n2025/09/21─2025/09/27\n\t休閒治療的組織與專業形成 \t \n3\t\n2025/09/28─2025/10/04\n\t休閒治療的發展過程 \t \n4\t\n2025/10/05─2025/10/11\n\t休閒治療在各領域的應用 \t \n5\t\n2025/10/12─2025/10/18\n\t休閒治療-精神與心智健康\n \t \n6\t\n2025/10/19─2025/10/25\n\t休閒治療-矯正社會異常 \t \n7\t\n2025/10/26─2025/11/01\n\t休閒治療-濫用問題的改善 \t \n8\t\n2025/11/02─2025/11/08\n\t休閒治療-自閉症的改善 \t \n9\t\n2025/11/09─2025/11/15\n\t休閒治療-智能障礙的排除 \t \n10\t\n2025/11/16─2025/11/22\n\t休閒治療-重度多重障礙的幫助\n \t \n11\t\n2025/11/23─2025/11/29\n\t休閒治療-神經肌肉病變的改善 \t \n12\t\n2025/11/30─2025/12/06\n\t休閒治療-認知復健 \t \n13\t\n2025/12/07─2025/12/13\n\t休閒治療-長老年人照護 \t \n14\t\n2025/12/14─2025/12/20\n\t休閒治療-兒童遊戲 \t \n15\t\n2025/12/21─2025/12/27\n\t休閒治療-心臟復健 \t \n16\t\n2025/12/28─2026/01/03\n\t小組報告 \t \n17\t\n2026/01/04─2026/01/10\n\t小組報告 \t \n18\t\n2026/01/11─2026/01/17\n\t小組報告 \t \n\n\n6.成績評定及課堂要求\n平時成績30% 小組討論報告40% 隨堂測驗30% \n勿遲到早退，不得缺席 \n \n\n\n8.永續發展目標(SDGs)：SDG3 健康與福祉\n\n\n9.大學社會責任(USR)關聯性：中"
}