{
    "semester": "114-2",
    "list_info": {
        "部別": "日間部學士班",
        "科系": "運動與休閒學系",
        "班級": "運休三",
        "選課代碼": "0640",
        "科目名稱": "休閒遊憩創業實務",
        "科目英文名": "Leisure Recreation Venture Practice",
        "學分": "2.0",
        "時數": "2.0",
        "必/選": "必修",
        "授課教師": "吳一德",
        "教室": "129運休系普通教室",
        "修課人數": "32",
        "上限人數": "60",
        "上課時間": "(二)1-2",
        "限修備註": "",
        "備註": ""
    },
    "detail_raw_text": "回上一頁\t國立金門大學\t \n \t教學綱要\t \n\n部別 : 日間部學士班\t114學年度第2學期\t列印日期 : 2026/05/24\n科目名稱 : 休閒遊憩創業實務 (Leisure Recreation Venture Practice)\t開課班級 : 運休三\t學　　分 : 2.0\t授課時數 : 2.0\n授課教師 : 吳一德\t必選修 : 必修\t \t \n\n\n1.教學目標\n1.瞭解創業的管理問題。 2.創業分析能力。 \n\n\n2.教學綱要\n針對創業做分析與論述，掌握創新創業時勢脈動。 \n\n\n3.教科書\n1\t書名 : 創新與創業　\n出版日期 : 年 月 \n作者 : 　出版社 : 華泰文化　版本 :  \n\n\n4.參考書\n1\t書名 : 　出版日期 : 年 月 \n作者 : 　出版社 : 　版本 :  \n2\t書名 : 　出版日期 : 年 月 \n作者 : 　出版社 : 　版本 :  \n\n※請遵守智慧財產權觀念，依著作權法規定，教科書及教材不得非法影印與使用盜版軟體。\n\n5.教學進度表\n週次\t日期\t內容\t備註\n1\t\n2026/02/22─2026/02/28\n\t課程介紹 \t \n2\t\n2026/03/01─2026/03/07\n\t你適合創辦企業嗎？ \t \n3\t\n2026/03/08─2026/03/14\n\t產生你的創業想法 \t \n4\t\n2026/03/15─2026/03/21\n\t分析並篩選出最好的企業想法 \t \n5\t\n2026/03/22─2026/03/28\n\t創新新思維 \t \n6\t\n2026/03/29─2026/04/04\n\t為自己建立一個好的商業模式. \t \n7\t\n2026/04/05─2026/04/11\n\t商業計畫書撰寫 \t \n8\t\n2026/04/12─2026/04/18\n\t評估市場 \t \n9\t\n2026/04/19─2026/04/25\n\t期中考 \t \n10\t\n2026/04/26─2026/05/02\n\t進入市場 \t \n11\t\n2026/05/03─2026/05/09\n\t企業型態選擇與創業相關法令 \t \n12\t\n2026/05/10─2026/05/16\n\t組織與人事 \t \n13\t\n2026/05/17─2026/05/23\n\t創業資金需求 \t \n14\t\n2026/05/24─2026/05/30\n\t成本與利潤計畫 \t \n15\t\n2026/05/31─2026/06/06\n\t現金流量預測 \t \n16\t\n2026/06/07─2026/06/13\n\t籌資與貸款 \t \n17\t\n2026/06/14─2026/06/20\n\t自主學習 \t \n18\t\n2026/06/21─2026/06/27\n\t自主學習 \t \n\n\n6.成績評定及課堂要求\n一、平時成績(15%)：出席率與學習態度。二、小考(15%)：隨堂考及發問。三、期中考(30%)：筆試。四、期末考(40%)：筆試或報告。 \n上課時，手機請關機以免影響師生上課品質。 \n \n\n\n8.永續發展目標(SDGs)：SDG11 永續城鄉、SDG12 責任消費及生產\n\n\n9.大學社會責任(USR)關聯性：中"
}